dag/__init__.py
dag/api.py
dag/main.py
gibs_imagestat-0.2.0a0.dist-info/LICENSE
gibs_imagestat-0.2.0a0.dist-info/WHEEL
gibs_imagestat-0.2.0a0.dist-info/METADATA
gibs_imagestat-0.2.0a0.dist-info/RECORD
