Metadata-Version: 2.1
Name: gibs-imagestat
Version: 0.2.0a0
Summary: Application capable of computing statistics on GIBS images
Home-page: https://github.com/podaac/gibs-imagestat
License: Apache-2.0
Author: podaac-tva
Author-email: podaac-tva@jpl.nasa.gov
Requires-Python: >=3.8,<4.0
Classifier: License :: OSI Approved :: Apache Software License
Classifier: Programming Language :: Python :: 3
Classifier: Programming Language :: Python :: 3.10
Classifier: Programming Language :: Python :: 3.8
Classifier: Programming Language :: Python :: 3.9
Requires-Dist: Pillow (>=9.0.1,<10.0.0)
Requires-Dist: beautifulsoup4 (>=4.10.0,<5.0.0)
Requires-Dist: fastapi (>=0.87,<0.88)
Requires-Dist: lxml (>=4.9.1,<5.0.0)
Requires-Dist: numpy (>=1.22.2,<2.0.0)
Requires-Dist: pandas (>=1.4.1,<2.0.0)
Requires-Dist: requests (>=2.27.1,<3.0.0)
Requires-Dist: starlette (>=0.21,<0.22)
Requires-Dist: urllib3 (>=1.26.8,<2.0.0)
Requires-Dist: uvicorn (>=0.19,<0.20)
Requires-Dist: xarray (>=2022.3.0,<2023.0.0)
Project-URL: Repository, https://github.com/podaac/gibs-imagestat
